tkinterdnd2/TkinterDnD.py
tkinterdnd2/__init__.py
tkinterdnd2/tkdnd/linux-arm64/libtkdnd2.9.3.so
tkinterdnd2/tkdnd/linux-arm64/pkgIndex.tcl
tkinterdnd2/tkdnd/linux-arm64/tkdnd.tcl
tkinterdnd2/tkdnd/linux-arm64/tkdnd_compat.tcl
tkinterdnd2/tkdnd/linux-arm64/tkdnd_generic.tcl
tkinterdnd2/tkdnd/linux-arm64/tkdnd_macosx.tcl
tkinterdnd2/tkdnd/linux-arm64/tkdnd_unix.tcl
tkinterdnd2/tkdnd/linux-arm64/tkdnd_utils.tcl
tkinterdnd2/tkdnd/linux-arm64/tkdnd_windows.tcl
tkinterdnd2/tkdnd/linux-x64/libtkdnd2.9.4.so
tkinterdnd2/tkdnd/linux-x64/pkgIndex.tcl
tkinterdnd2/tkdnd/linux-x64/tkdnd.tcl
tkinterdnd2/tkdnd/linux-x64/tkdnd_compat.tcl
tkinterdnd2/tkdnd/linux-x64/tkdnd_generic.tcl
tkinterdnd2/tkdnd/linux-x64/tkdnd_macosx.tcl
tkinterdnd2/tkdnd/linux-x64/tkdnd_unix.tcl
tkinterdnd2/tkdnd/linux-x64/tkdnd_utils.tcl
tkinterdnd2/tkdnd/linux-x64/tkdnd_windows.tcl
tkinterdnd2/tkdnd/osx-arm64/libtkdnd2.9.3.dylib
tkinterdnd2/tkdnd/osx-arm64/pkgIndex.tcl
tkinterdnd2/tkdnd/osx-arm64/tkdnd.tcl
tkinterdnd2/tkdnd/osx-arm64/tkdnd_compat.tcl
tkinterdnd2/tkdnd/osx-arm64/tkdnd_generic.tcl
tkinterdnd2/tkdnd/osx-arm64/tkdnd_macosx.tcl
tkinterdnd2/tkdnd/osx-arm64/tkdnd_unix.tcl
tkinterdnd2/tkdnd/osx-arm64/tkdnd_utils.tcl
tkinterdnd2/tkdnd/osx-arm64/tkdnd_windows.tcl
tkinterdnd2/tkdnd/osx-x64/libtkdnd2.9.4.dylib
tkinterdnd2/tkdnd/osx-x64/pkgIndex.tcl
tkinterdnd2/tkdnd/osx-x64/tkdnd.tcl
tkinterdnd2/tkdnd/osx-x64/tkdnd_compat.tcl
tkinterdnd2/tkdnd/osx-x64/tkdnd_generic.tcl
tkinterdnd2/tkdnd/osx-x64/tkdnd_macosx.tcl
tkinterdnd2/tkdnd/osx-x64/tkdnd_unix.tcl
tkinterdnd2/tkdnd/osx-x64/tkdnd_utils.tcl
tkinterdnd2/tkdnd/osx-x64/tkdnd_windows.tcl
tkinterdnd2/tkdnd/win-arm64/libtkdnd2.9.3.dll
tkinterdnd2/tkdnd/win-arm64/pkgIndex.tcl
tkinterdnd2/tkdnd/win-arm64/tkdnd.tcl
tkinterdnd2/tkdnd/win-arm64/tkdnd2.9.3.lib
tkinterdnd2/tkdnd/win-arm64/tkdnd_compat.tcl
tkinterdnd2/tkdnd/win-arm64/tkdnd_generic.tcl
tkinterdnd2/tkdnd/win-arm64/tkdnd_macosx.tcl
tkinterdnd2/tkdnd/win-arm64/tkdnd_unix.tcl
tkinterdnd2-0.4.1.dist-info/LICENSE
tkinterdnd2-0.4.1.dist-info/METADATA
tkinterdnd2-0.4.1.dist-info/WHEEL
tkinterdnd2-0.4.1.dist-info/top_level.txt
tkinterdnd2-0.4.1.dist-info/RECORD
